README.md
ez_setup.py
setup.py
gett/__init__.py
gett/gett.py
gett/uploader.py
gett_cli.egg-info/PKG-INFO
gett_cli.egg-info/SOURCES.txt
gett_cli.egg-info/dependency_links.txt
gett_cli.egg-info/entry_points.txt
gett_cli.egg-info/top_level.txt