Metadata-Version: 1.0
Name: gett-cli
Version: 0.2.3
Summary: A command-line Ge.tt uploader and manager
Home-page: https://bitbucket.org/mickael9/gett-cli/
Author: Mickaël THOMAS
Author-email: mickael9@gmail.com
License: UNKNOWN
Platform: UNKNOWN
